{
  "url": "https://www.saflii.org/za/cases/ZAGPPHC/2021/198.html",
  "scraped_at": "2026-05-20T13:35:36.171780",
  "case_number": "",
  "court": "",
  "date": "",
  "accused": "",
  "charges": [
    "murder",
    "kidnapping",
    "robbery",
    "assault"
  ],
  "verdict": "Not Guilty",
  "sentence": "life imprisonment",
  "province": "Gauteng",
  "full_text": "Letsiri and Another v S (A689/2016) [2021] ZAGPPHC 198 (1 April 2021)\nAbout SAFLII\nDatabases\nSearch\nTerms of Use\nRSS Feeds\nSouth Africa: North Gauteng High Court, Pretoria\nYou are here:\nSAFLII\n>>\nDatabases\n>>\nSouth Africa: North Gauteng High Court, Pretoria\n>>\n2021\n>>\n[2021] ZAGPPHC 198\n|\nNoteup\n|\nLawCite\nLetsiri and Another v S (A689/2016) [2021] ZAGPPHC 198 (1 April 2021)\nDownload original files\nPDF format\nRTF format\nSAFLII\nNote:\nCertain\npersonal/private details of parties or witnesses have been redacted\nfrom this document in compliance with the law and\nSAFLII\nPolicy\nIN\nTHE\nHIGH\nCOURT\nOF\nSOUTH\nAFRICA\nGAUTENG\nDIVISION\nCase\nNumber: A689/2016 Date: 18 November 2020\nREPORTABLE:YES/NO\nOF\nINTEREST TO OTHER JUDGES:YES/NO\nREVISED\nDATE:01\nAPRIL 2021\nKOBOPHIRI\nSMODEN LETSIRI                                         \nFIRST APPELLANT\nCEDRICK\nNKADIMENG                                                 \nSECOND\nAPPELLANT\nand\nTHE\nSTATE                                                                                       \nRESPONDENT\nThis\njudgment is issued by the Judge whose name is reflected herein and is\nsubmitted electronically to the Parties/their legal representatives\nby email. The judgment is further uploaded to the electronic file of\nthis matter on CaseLines by the Judge or his/her Secretary.\nThe\ndate\nof this judgment is\ndeemed to\nbe 01 April 2021.\nJUDGMENT\nLUKHAIMANE\n  AJ:\n[1]         \nThe First Appellant (Accused 1 in the trial court) stood trial in the\nregional court, Pretoria, along with two others, on the following\ncharges:\n(a)     \nCount 1: Murder read with Section 51(2) of the Criminal Law Amendment\nAct, Act 105 of 1997;\n(a)      \nCount 2: Kidnapping;\n(b)      \nCount 3: Murder read with section 51(2) of Act 105 of 1997;\n(c)      \nCount 4: Kidnapping;\n(d)     \nCount 5: Murder read with section 51(2) of Act 105 of 1997;\n(e)      \nCount 6: Kidnapping;\n(f)       \nCount 7: Assault with the intent to cause grievous bodily harm;\n(g)     \nCount 8: Kidnapping\n[2]         \nThe First Appellant was legally represented at the time of his trial,\nhad pleaded not guilty and was convicted on all counts. The presiding\nmagistrate had found that the deceased were all killed during\nthe\nsame incident, together with the assault on the complainant.\n[3]         \nThe matter came before this court on petition directed to the Judge\nPresident\nfor leave to appeal the Appellants’ conviction and\nsentence. The trial court had refused such leave to appeal on 21\nApril\n2016. On petition, leave to appeal was refused on conviction,\nhowever granted on sentence. Although leave to appeal was granted\nto\nboth Appellants, only the First Appellant has persisted with the\nappeal. Therefor-e, this judgment is only in respect of the\nFirst\nAppellant.\n[4]         \nApplications for leave to appeal a conviction and/or sentence imposed\nby a Magistrate Court are governed by\nsection 3098\nof the\nCriminal\nProcedure Act 51 of 1977\nand upon such leave being refused, on\npetition to the Judge President in terms of\nsection 309C\nof the same\nAct.\n[5]\nOn 23 March 2015, the First Appellant was convicted by the\npresiding magistrate. The trial court held as follows:\n“\nYou\nhave been convicted on all counts but regarding murder, it will be\na\ncondition\nunder section 51(2). I will elaborate myself on section 51(2) and (1)\nduring the sentencing status.”\n[1]\n[6]         \nOn 14 July 2015, the 1\nst\nAppellant was sentenced to an\neffective sentence of 52 years of imprisonment as follows:\n(a)     \nCount 1: Murder                                       \n-15 years of imprisonment\n(b)     \nCount 2: Kidnapping                               \n-1 year imprisonment\n(c)      \nCount 3: Murder                                       \n-15 years of imprisonment\n(d)     \nCount 4: Kidnapping                               \n-1 year imprisonment\n(e)     \nCount 5: Murder                                       \n-15 years imprisonment\n(f)       \nCount 6: Kidnapping                               \n-1 year imprisonment\n(g)     \nCount 7: Assault with the intent to      \n-3 years imprisonment\ncause\ngrievous bodily harm\n(h)     \nCount 8: Kidnapping                               \n-1 year imprisonment\n[7]\nAlthough\nthe effective sentence is 52 years of imprisonment, the trial court\nnoted that the effective sentence was 51 years of imprisonment.\n[2]\n[8]\nThe\norigins of the conviction and the sentence arose from events which\noccurred on 29 November 2009. The First Appellant, together\nwith two\nothers,\nwere\npart of a community mob that hunted down the deceased, assaulted them\nwith sticks, stones and a variety of tools, killing\nthem\non\na\nhill\nas\nthey\nsuspected\nthe\ndeceased of stealing the First Appellant's vehicle whilst parked\noutside Chamberlains\nStore\nin Watloo, Pretoria.\n[9]\nIn\nsentencing the First Appellant, the trial court found that the three\ndeceased were killed in a cold and calculated manner; a\ngrossly\nbarbaric manner that does not belong in a civilised society grounded\nin\nthe\nrule of law. The trial court also found that the Appellants hunted\ndown the deceased thereby establishing\npremeditation.\nThe trial court\nalso\nfound\nthat\nthe\nmurder\nwas\npremeditated\n[10]\nFor\npurposes of mitigation of sentence, the following personal\ncircumstances of the First Appellant were placed on record by his\nlegal representative:\n-     \nFirst Appellant was […]years old at the time of imposition of\nsentence;\n-     \nHe was unemployed, but earned an income doing casual work;\n-     \nHe is married;\n-     \nHe has 5 children born between 1994 and 2000;\n-     \nThe family relied on social grants for the younger children;\n-     \nHe was a first offender;\n-     \nHe had no history of violent behaviour;\n-     \nThe older 3 children no longer receive social grants and are\nunmarried;\n-     \nHis parents passed away when he was very young;\n-     \nHe did not attend school.\n[11]      \nThe only mitigating factors placed before the trial court were his\npersonal circumstances,\nhis age and the fact that he had no previous\nconvictions.\n[12]      \nThe legal representative of the First Appellant did not argue any\nsubstantial and compelling\ncircumstances present which would justify\na deviataion from the prescribed minimum sentences. His argument\ninstead was that the\ntrial court ought to impose the prescribed\nminimum sentence in terms of section 51(2) of Act 105 of 1997, being\n15 years imprisonment.\nThe trial court found no substantial and\ncompelling circumstances; therefore, there was no justification to\ndeviate from the prescribed\nminimum sentences to impose a\nlesser-sentence.\n[13]      \nCounsel for the Respondent on the other hand submitted that the First\nAppellant was part\nof a group, which formed a premeditated action,\nthat there were no substantial and compelling circumstances to\ndeviate from the\nprescribed sentence, nor were any argued during the\nsentencing process. Therefore, the Respondent argues that in the\nabsence of\nany misdirection on the part of the trial court, that the\nappeal court must not interfere with the sentences imposed by the\ncourt\na quo.\n[14]    \nSection 51(2) of Act 105 of 1997 on which the First Appellant was\nconvicted, provides as follows:\n“\n(2)     \nNotwithstanding any other law, but subject to subsections (3) and\n(6),\na\nregional court of\na\nHigh Court shall\n-\n(i)     \nIf it has convicted\na\nperson\nof\nan\noffence\nreferred\nto in\nPart\nII\nof\nSchedule 2 sentence the\nperson, in the case of\n-\n(i)     \nA first offender, to imprisonment for\na\nperiod not less than\n15 years\n...\nProvided\nthat the maximum sentence that\na\nregional court may impose in\nterms\nof this subsection shall not be more than five\nyears longer than the minimum sentence that it may impose in terms of\nthis subsection.\"\n[15]\n    It is well established in our law that\nsentencing is within the discretion of the sentencing court.\nThe\nappeal court would normally not interfere with such discretion unless\nthe discretion is found to have been improperly exercised.\nTherefore,\nsuch inquiry is not on whether the sentence was right or wrong but\nwhether the discretion was exercised properly and\njudicially”.\n[3]\n[16]    \nSection 51(2) of Act 105 of 1997 provides for a prescribed minimum\nsentence of 15 years imprisonment\nfor a first offender accused of\nmurder. In addition, section 51(3) of Act 105 of 1997 provides that\nthe trial court must impose\na sentence that is less than the\nprescribed minimum sentence were the court to find substantial and\ncompelling circumstances justifying\nthat a lesser sentence\nbe\nimposed\n[17]\nIn\nrespect of the First Appellant, no substantial and compelling\ncircumstances were placed before the court and the trial court\non its\nown could not establish any substantial and compelling circumstances.\nOnly his personal circumstances as indicated in paragraph\n10 above,\nwere placed before the trial\ncourt.\n[18]\nOn\nbehalf of the First Appellant, it was submitted that the trial court\ndid not properly consider the cumulative effect of the imposed\nsentences, taking into account the First Appellant's personal\ncircumstances. Counsel for the First Appellant relied on\nS\nv Mahlatsi\n[4]\n,\nwhere the court held that the effective sentences under section 51(1)\nor (2) of the Criminal Law Amendment Act should not exceed\nlife\nimprisonment:\n“\nThe\nappellant\nwas\nconvicted\nin\nthe\nhigh\ncourt\non\nthree\ncounts\nof armed robbery and one count of kidnapping arising out of\na\nseries\nof armed robberies in which\nthe\nappellant, together with\na\nnumber\nof associates, set out on\na\nspree\nof robberies\nand\ncar hijackings.\nHe\nwas sentenced\nto\nthe minimum\nsentence\nof\n15 years’ imprisonment on each of the robbery counts and five\nyears’ imprisonment on the count of kidnapping. None\nof the\nsentences were ordered\nto\nrun concurrently\n-\nthe\neffective sentence therefore being 50 years’ imprisonment.”\n[5]\nThe\ncourt held as follows:\n“\nthat\nthe only attack against the sentence imposed on the appellant that\nhad, at\nleast,\nsome merit was that the cumulative effect thereof could arguably be\nperceived to be too heavy. The effective gaol term of\n50 years’\nimprisonment was an exceptionally long time by anyone's standard, ad\nthis raised the question of the maximum term\nof imprisonment\nthat\nshould be imposed if life imprisonment were not imposed, or where\na\nconvicted\nperson had not been declared\na\nhabitual\ncriminal or\na\ndangerous\ncriminal in terms of\nss 286\n,\n286A\nand\n2868\nof the\nCriminal Procedure\nAct 51 of 1977\n.”\n[6]\n[19]\nCourts\nhave several avenues available to them to ensure that the cumulative\neffect of sentences is mitigated, the most prevalent\nbeing to order\nthat parts of\nsentences\nrun concurrent.\n[7]\n[20]\nIt\nis therefore the First Appellant’s submission that to curb the\ncumulative effect\nof\nthe sentences, the trial court should have made the kidnapping\ncharges run concurrent with the murder charges as well as the\nassault\ncharge - resulting in\nan\neffective sentence of 48 years imprisonment. The Respondent on the\nother hand submits that in the absence of any misdirection\non the\npart of the trial court, this Honourable court must not interfere\nwith the trial court’s sentence and the appeal should\ntherefore\nfail.\n[21]\nThis\ncourt is being asked to consider whether the cumulative effect of the\nsentences was too severe, thereby resulting in a misdirection\nthat\nwould justify\ninterference.\nIn terms of the cumulative effect of the sentence, none of the\ncharges individually warranted a life imprisonment\nsentence. However,\nthe effective sentence is equal to imposing a sentence which has the\neffect of permanently removing the Appellant\nfrom society. This\neffective sentence is 52\nyears\nimprisonment, even though the trial court noted it as 51 years of\nimprisonment\n[8]\nand therefore\nmore onerous than a life sentence because for a person sentenced to\nlife imprisonment,\nconsideration\nfor\nrelease on parole may be after 25 years imprisonment.\n[9]\n[22]\nIn\nZimila v S\n[10]\n,   Shongwe\nADP at paragraph 10 states as follows:\n“\nThe\nregional court,\nas\nwell\nas\nthe court\na\nquo,\nconsidered all the purposes of punishment, the personal circumstances\nof the appellant, the seriousness of the offences and\nthe interests\nof society. There is no need to repeat same. The area of interference\nwill be in respect of making certain sentences\nto run concurrently\nwith\ncount\n1\nand\nthe\nsentences in\ncounts\n13\nand\n15\nto\nrun concurrently. The logic\nis that when considering an appropriate sentence, the regional court\nconsidered all the necessary factors,\ntherefore, since the offences\nare similar in nature, it would serve the interests of justice to\nmitigate the length of the sentence\nby ordering some of the counts to\nrun concurrently.\n”\n[23]      \nAs the offences that were committed were closely connected to each\nother in time and space,\nit is so that the learned magistrate should\nhave ordered the sentences to run concurrently. In granting the\nsentences, the learned\nmagistrate neglected to do this. The appeal on\nsentence must therefore succeed. Having regard to that, I therefore\n“propose\nwhat is stated in the order below to be an appropriate\neffective sentence, taking into account the cumulative effect of the\nindividual\nsentences.\n[24]      \nThe following order is made:\n1.        \nThe appeal is upheld.\n2.        \nThe order of the court a quo is set aside and replaced with the\nfollowing:\n(a)     \nCount 1: Murder                                 \n- 15 years of imprisonment\n(b)     \nCount 2: Kidnapping                         \n- 1 year of imprisonment\n(c)     \nCount 3: Murder                                 \n- 15 years of imprisonment\n(d)     \nCount 4: Kidnapping                        \n- 1 year of imprisonment\n(e)     \nCount 5: Murder                                 \n- 15 years of imprisonment\n(f)       \nCount 6: Kidnapping                        \n- 1 year of imprisonment\n(g)     \nCount 7: Assault with the intent to      - 3\nyears of imprisonment\ncause\ngrievous bodily harm\n(h)     \nCount 8: Kidnapping                        \n- 1 year of imprisonment\n(i)       \nThe sentences imposed in respect of Counts 2,4 and 6 are ordered to\nrun concurrently\nwith the sentences in Counts 1,3 and 5,\nrespectively, in terms of section 280(2) of the Criminal Procedure\nAct 51 of 1977.\n(j)\n    The sentence imposed in terms of Count 8 is\nordered to run concurrently with the sentence in count 7, in\nterms of\nsection 280(2) of the Criminal Procedure Act 51 of 1977.\n(k)         \nEffectively, the Appellant is sentenced to 48 years’\nimprisonment.\n(I)           \nThe sentences are antedated to 14 July 2015 in terms of\nsection 282\nof the\nCriminal Procedure Act 51 of 1977\n.\nMA\n LUKHAIMANE\nACTING\nJUDGE OF THE HIGH COURT\nI\nagree\nCJ\n COLLIS\nJUDGE\nOF THE HIGH COURT\nFor\nthe First Appellant                :\nAdv. L.A van\nWyk\nInstructed\nby         \n:           Legal Aid SA\nFor\nthe Respondent        \n:\n          Adv. L\nWilliams\nInstructed\nby         \n                      :\n          Director of\nPublic Prosecutions\nDate\nof Hearing                           \n:           18 November\n2020\nDate\nof Judgment                        \n:           01 April\n2021\n[1]\nRecord p 691lines 21-\n23\n[2]\nRecord p 803 lines 17-19\n[3]\nS v Rabie 1975 (4) SA 855 (A)\n[4]\n2013 (2) SACR 625\n(GNP)\n[5]\n2013 (2) SACR 625\n(GNP)\n\tat\npar\n\t4\n[6]\n2013 (2) SACR 625\n(GNP)\n\tat par 4\n[7]\nSection 280\n(2) of the\nCriminal Procedure Act 51 of 1977\n[8]\nRecord p 803 lines 17-19\n[9]\nS\nv\nMahlakaza\n\t& Another 1997 (1)\n1997 SACR 515\n(SCA) at 521 G-1);\nands\n\t73(6) of\nthe\nCorrectional\nServices Act 111 of 1998\n[10]\n2017 ZASCA 55\n(18 May 2017)",
  "summary": "Letsiri and Another v S (A689/2016) [2021] ZAGPPHC 198 (1 April 2021) About SAFLII Databases Search Terms of Use RSS Feeds South Africa: North Gauteng High Court, Pretoria You are here: SAFLII >> Databases >> South Africa: North Gauteng High Court, Pretoria >> 2021 >> [2021] ZAGPPHC 198 | Noteup | LawCite Letsiri and Another v S (A689/2016) [2021] ZAGPPHC 198 (1 April 2021) Download original files PDF format RTF format SAFLII Note: Certain personal/private details of parties or witnesses have been redacted from this document in compliance with the law and SAFLII Policy IN THE HIGH COURT OF SOUTH AFRICA GAUTENG DIVISION Case Number: A689/2016 Date: 18 November 2020 REPORTABLE:YES/NO OF INTEREST TO OTHER JUDGES:YES/NO REVISED DATE:01 APRIL 2021 KOBOPHIRI SMODEN LETSIRI                                          FIRST APPELLANT CEDRICK NKADIMENG                                                  SECOND APPELLANT and THE STATE"
}